<?xml version="1.0" encoding="utf-8"?>
<openerp>
    <data>
    
        <!-- 18/02/2015 (felix) Modificación de formulario para registro de Números de lote -->
        <record id="stock.action_production_lot_form" model="ir.actions.act_window">
            <field name="name">Números de lote</field>
            <field name="type">ir.actions.act_window</field>
            <field name="res_model">stock.production.lot</field>
            <field name="view_type">form</field>
            <field name="view_id" ref="stock.view_production_lot_tree"/>
            <field name="search_view_id" ref="stock.search_product_lot_filter"/>
            <field name="context">{}</field>
            <field name="help" type="html">
              <p class="oe_view_nocontent_create">
                Click to add a serial number.
              </p><p>
                This is the list of all the production lots you recorded. When
                you select a lot, you can get the upstream or downstream
                traceability of the products contained in lot. By default, the
                list is filtred on the serial numbers that are available in
                your warehouse but you can uncheck the 'Available' button to
                get all the lots you produced, received or delivered to
                customers.
              </p>
            </field>
        </record>
    
        <!-- 18/02/2015 (felix) Modificación de formulario para registro de Números de lote 
            Almacén -> Trazabilidad -> Números de lote
        -->
        <record id="view_move_form_expiry_inherit_1" model="ir.ui.view">
            <field name="name">view.move.form.expiry.inherit.1</field>
            <field name="model">stock.production.lot</field>
            <field name="inherit_id" ref="product_expiry.view_move_form_expiry"/>
            <field name="arch" type="xml">
                                
                <!-- 18/02/2015 (felix) (+) Ocultar "Fecha de fin de vida" -->
                <xpath expr="//field[@name='life_date']" position="replace">
                    <field name="life_date" invisible="1"/>
                </xpath>
                
                <!-- 18/02/2015 (felix) (+) Ocultar "Fecha de eliminación" -->
                <xpath expr="//field[@name='removal_date']" position="replace">
                    <field name="removal_date" invisible="1"/>
                </xpath>
                                
                <!-- 18/02/2015 (felix) (+) Crear como campos obligagorios "Fecha de caducidad" -->
                <xpath expr="//field[@name='use_date']" position="replace">
                    <field name="use_date" string="Fecha de caducidad" required="1"/>
                </xpath>
                
                <!-- 18/02/2015 (felix) 
                    (+) Crear como campos obligagorios "Fecha de retest" 
                    (+) Cambiar etiqueta "Fecha de alerta" por "Fecha de retest"
                -->
                <xpath expr="//field[@name='alert_date']" position="replace">
                    <field name="alert_date" string="Fecha de retest" required="1"/>
                </xpath>
                
            </field>
        </record>
        
    </data>
</openerp>
